led_blink.v
`timescale 1ns / 1ps

module led_blink (
    input  wire        sysclk,               // your 125 MHz fabric clock
    output reg  [3:0]  led      // 4 LEDs from base.xdc
);

  // 27-bit counter: bit[26] toggles at roughly 125 MHz / 2^27 ? 0.93 Hz
  reg [26:0] counter = 0;

  always @(posedge sysclk) begin
    counter <= counter + 1;
    // Blink LED0, keep others off
//    led[0] <= counter[26];
    led[0] <= counter[24];
    led[1] <= counter[25];
    led[2] <= counter[26];
    led[3] <= 1'b0;
  end

endmodule

tb_led_blink.v
`timescale 1ns/1ps
`include "led_blink.v"  // for iverilog simulation only

module tb_led_blink;

  // Testbench signals
  reg sysclk;
  wire [3:0] led;

  // Instantiate DUT
  led_blink uut (
    .sysclk(sysclk),
    .led(led)
  );

  // Clock generator: 125 MHz = 8 ns period
  initial sysclk = 0;
  always #4 sysclk = ~sysclk;  // Toggle every 4 ns

  // Run simulation
  initial begin
    // Run for some time and dump waveform
    $dumpfile("led_blink.vcd");  // for GTKWave if needed
    $dumpvars(0, tb_led_blink);
    $monitor("Time: %0dns, LED: %b", $time, led);

    #2000;   // Run for 1ns
    $finish;
  end

endmodule

led_blink.vcd
$date
	Sun Aug 31 11:50:38 2025
$end
$version
	Icarus Verilog
$end
$timescale
	1ps
$end
$scope module tb_led_blink $end
$var wire 4 ! led [3:0] $end
$var reg 1 " sysclk $end
$scope module uut $end
$var wire 1 " sysclk $end
$var reg 27 # counter [26:0] $end
$var reg 4 $ led [3:0] $end
$upscope $end
$upscope $end
$enddefinitions $end
$comment Show the parameter values. $end
$dumpall
$end
#0
$dumpvars
bx $
b0 #
0"
bx !
$end
#4000
b0 !
b0 $
b1 #
1"
#8000
0"
#12000
b10 #
1"
#16000
0"
#20000
b11 #
1"
#24000
0"
#28000
b100 #
1"
#32000
0"
#36000
b101 #
1"
#40000
0"
#44000
b110 #
1"
#48000
0"
#52000
b111 #
1"
#56000
0"
#60000
b1000 #
1"
#64000
0"
#68000
b1001 #
1"
#72000
0"
#76000
b1010 #
1"
#80000
0"
#84000
b1011 #
1"
#88000
0"
#92000
b1100 #
1"
#96000
0"
#100000
b1101 #
1"
#104000
0"
#108000
b1110 #
1"
#112000
0"
#116000
b1111 #
1"
#120000
0"
#124000
b10000 #
1"
#128000
0"
#132000
b10001 #
1"
#136000
0"
#140000
b10010 #
1"
#144000
0"
#148000
b10011 #
1"
#152000
0"
#156000
b10100 #
1"
#160000
0"
#164000
b10101 #
1"
#168000
0"
#172000
b10110 #
1"
#176000
0"
#180000
b10111 #
1"
#184000
0"
#188000
b11000 #
1"
#192000
0"
#196000
b11001 #
1"
#200000
0"
#204000
b11010 #
1"
#208000
0"
#212000
b11011 #
1"
#216000
0"
#220000
b11100 #
1"
#224000
0"
#228000
b11101 #
1"
#232000
0"
#236000
b11110 #
1"
#240000
0"
#244000
b11111 #
1"
#248000
0"
#252000
b100000 #
1"
#256000
0"
#260000
b100001 #
1"
#264000
0"
#268000
b100010 #
1"
#272000
0"
#276000
b100011 #
1"
#280000
0"
#284000
b100100 #
1"
#288000
0"
#292000
b100101 #
1"
#296000
0"
#300000
b100110 #
1"
#304000
0"
#308000
b100111 #
1"
#312000
0"
#316000
b101000 #
1"
#320000
0"
#324000
b101001 #
1"
#328000
0"
#332000
b101010 #
1"
#336000
0"
#340000
b101011 #
1"
#344000
0"
#348000
b101100 #
1"
#352000
0"
#356000
b101101 #
1"
#360000
0"
#364000
b101110 #
1"
#368000
0"
#372000
b101111 #
1"
#376000
0"
#380000
b110000 #
1"
#384000
0"
#388000
b110001 #
1"
#392000
0"
#396000
b110010 #
1"
#400000
0"
#404000
b110011 #
1"
#408000
0"
#412000
b110100 #
1"
#416000
0"
#420000
b110101 #
1"
#424000
0"
#428000
b110110 #
1"
#432000
0"
#436000
b110111 #
1"
#440000
0"
#444000
b111000 #
1"
#448000
0"
#452000
b111001 #
1"
#456000
0"
#460000
b111010 #
1"
#464000
0"
#468000
b111011 #
1"
#472000
0"
#476000
b111100 #
1"
#480000
0"
#484000
b111101 #
1"
#488000
0"
#492000
b111110 #
1"
#496000
0"
#500000
b111111 #
1"
#504000
0"
#508000
b1000000 #
1"
#512000
0"
#516000
b1000001 #
1"
#520000
0"
#524000
b1000010 #
1"
#528000
0"
#532000
b1000011 #
1"
#536000
0"
#540000
b1000100 #
1"
#544000
0"
#548000
b1000101 #
1"
#552000
0"
#556000
b1000110 #
1"
#560000
0"
#564000
b1000111 #
1"
#568000
0"
#572000
b1001000 #
1"
#576000
0"
#580000
b1001001 #
1"
#584000
0"
#588000
b1001010 #
1"
#592000
0"
#596000
b1001011 #
1"
#600000
0"
#604000
b1001100 #
1"
#608000
0"
#612000
b1001101 #
1"
#616000
0"
#620000
b1001110 #
1"
#624000
0"
#628000
b1001111 #
1"
#632000
0"
#636000
b1010000 #
1"
#640000
0"
#644000
b1010001 #
1"
#648000
0"
#652000
b1010010 #
1"
#656000
0"
#660000
b1010011 #
1"
#664000
0"
#668000
b1010100 #
1"
#672000
0"
#676000
b1010101 #
1"
#680000
0"
#684000
b1010110 #
1"
#688000
0"
#692000
b1010111 #
1"
#696000
0"
#700000
b1011000 #
1"
#704000
0"
#708000
b1011001 #
1"
#712000
0"
#716000
b1011010 #
1"
#720000
0"
#724000
b1011011 #
1"
#728000
0"
#732000
b1011100 #
1"
#736000
0"
#740000
b1011101 #
1"
#744000
0"
#748000
b1011110 #
1"
#752000
0"
#756000
b1011111 #
1"
#760000
0"
#764000
b1100000 #
1"
#768000
0"
#772000
b1100001 #
1"
#776000
0"
#780000
b1100010 #
1"
#784000
0"
#788000
b1100011 #
1"
#792000
0"
#796000
b1100100 #
1"
#800000
0"
#804000
b1100101 #
1"
#808000
0"
#812000
b1100110 #
1"
#816000
0"
#820000
b1100111 #
1"
#824000
0"
#828000
b1101000 #
1"
#832000
0"
#836000
b1101001 #
1"
#840000
0"
#844000
b1101010 #
1"
#848000
0"
#852000
b1101011 #
1"
#856000
0"
#860000
b1101100 #
1"
#864000
0"
#868000
b1101101 #
1"
#872000
0"
#876000
b1101110 #
1"
#880000
0"
#884000
b1101111 #
1"
#888000
0"
#892000
b1110000 #
1"
#896000
0"
#900000
b1110001 #
1"
#904000
0"
#908000
b1110010 #
1"
#912000
0"
#916000
b1110011 #
1"
#920000
0"
#924000
b1110100 #
1"
#928000
0"
#932000
b1110101 #
1"
#936000
0"
#940000
b1110110 #
1"
#944000
0"
#948000
b1110111 #
1"
#952000
0"
#956000
b1111000 #
1"
#960000
0"
#964000
b1111001 #
1"
#968000
0"
#972000
b1111010 #
1"
#976000
0"
#980000
b1111011 #
1"
#984000
0"
#988000
b1111100 #
1"
#992000
0"
#996000
b1111101 #
1"
#1000000
0"
#1004000
b1111110 #
1"
#1008000
0"
#1012000
b1111111 #
1"
#1016000
0"
#1020000
b10000000 #
1"
#1024000
0"
#1028000
b10000001 #
1"
#1032000
0"
#1036000
b10000010 #
1"
#1040000
0"
#1044000
b10000011 #
1"
#1048000
0"
#1052000
b10000100 #
1"
#1056000
0"
#1060000
b10000101 #
1"
#1064000
0"
#1068000
b10000110 #
1"
#1072000
0"
#1076000
b10000111 #
1"
#1080000
0"
#1084000
b10001000 #
1"
#1088000
0"
#1092000
b10001001 #
1"
#1096000
0"
#1100000
b10001010 #
1"
#1104000
0"
#1108000
b10001011 #
1"
#1112000
0"
#1116000
b10001100 #
1"
#1120000
0"
#1124000
b10001101 #
1"
#1128000
0"
#1132000
b10001110 #
1"
#1136000
0"
#1140000
b10001111 #
1"
#1144000
0"
#1148000
b10010000 #
1"
#1152000
0"
#1156000
b10010001 #
1"
#1160000
0"
#1164000
b10010010 #
1"
#1168000
0"
#1172000
b10010011 #
1"
#1176000
0"
#1180000
b10010100 #
1"
#1184000
0"
#1188000
b10010101 #
1"
#1192000
0"
#1196000
b10010110 #
1"
#1200000
0"
#1204000
b10010111 #
1"
#1208000
0"
#1212000
b10011000 #
1"
#1216000
0"
#1220000
b10011001 #
1"
#1224000
0"
#1228000
b10011010 #
1"
#1232000
0"
#1236000
b10011011 #
1"
#1240000
0"
#1244000
b10011100 #
1"
#1248000
0"
#1252000
b10011101 #
1"
#1256000
0"
#1260000
b10011110 #
1"
#1264000
0"
#1268000
b10011111 #
1"
#1272000
0"
#1276000
b10100000 #
1"
#1280000
0"
#1284000
b10100001 #
1"
#1288000
0"
#1292000
b10100010 #
1"
#1296000
0"
#1300000
b10100011 #
1"
#1304000
0"
#1308000
b10100100 #
1"
#1312000
0"
#1316000
b10100101 #
1"
#1320000
0"
#1324000
b10100110 #
1"
#1328000
0"
#1332000
b10100111 #
1"
#1336000
0"
#1340000
b10101000 #
1"
#1344000
0"
#1348000
b10101001 #
1"
#1352000
0"
#1356000
b10101010 #
1"
#1360000
0"
#1364000
b10101011 #
1"
#1368000
0"
#1372000
b10101100 #
1"
#1376000
0"
#1380000
b10101101 #
1"
#1384000
0"
#1388000
b10101110 #
1"
#1392000
0"
#1396000
b10101111 #
1"
#1400000
0"
#1404000
b10110000 #
1"
#1408000
0"
#1412000
b10110001 #
1"
#1416000
0"
#1420000
b10110010 #
1"
#1424000
0"
#1428000
b10110011 #
1"
#1432000
0"
#1436000
b10110100 #
1"
#1440000
0"
#1444000
b10110101 #
1"
#1448000
0"
#1452000
b10110110 #
1"
#1456000
0"
#1460000
b10110111 #
1"
#1464000
0"
#1468000
b10111000 #
1"
#1472000
0"
#1476000
b10111001 #
1"
#1480000
0"
#1484000
b10111010 #
1"
#1488000
0"
#1492000
b10111011 #
1"
#1496000
0"
#1500000
b10111100 #
1"
#1504000
0"
#1508000
b10111101 #
1"
#1512000
0"
#1516000
b10111110 #
1"
#1520000
0"
#1524000
b10111111 #
1"
#1528000
0"
#1532000
b11000000 #
1"
#1536000
0"
#1540000
b11000001 #
1"
#1544000
0"
#1548000
b11000010 #
1"
#1552000
0"
#1556000
b11000011 #
1"
#1560000
0"
#1564000
b11000100 #
1"
#1568000
0"
#1572000
b11000101 #
1"
#1576000
0"
#1580000
b11000110 #
1"
#1584000
0"
#1588000
b11000111 #
1"
#1592000
0"
#1596000
b11001000 #
1"
#1600000
0"
#1604000
b11001001 #
1"
#1608000
0"
#1612000
b11001010 #
1"
#1616000
0"
#1620000
b11001011 #
1"
#1624000
0"
#1628000
b11001100 #
1"
#1632000
0"
#1636000
b11001101 #
1"
#1640000
0"
#1644000
b11001110 #
1"
#1648000
0"
#1652000
b11001111 #
1"
#1656000
0"
#1660000
b11010000 #
1"
#1664000
0"
#1668000
b11010001 #
1"
#1672000
0"
#1676000
b11010010 #
1"
#1680000
0"
#1684000
b11010011 #
1"
#1688000
0"
#1692000
b11010100 #
1"
#1696000
0"
#1700000
b11010101 #
1"
#1704000
0"
#1708000
b11010110 #
1"
#1712000
0"
#1716000
b11010111 #
1"
#1720000
0"
#1724000
b11011000 #
1"
#1728000
0"
#1732000
b11011001 #
1"
#1736000
0"
#1740000
b11011010 #
1"
#1744000
0"
#1748000
b11011011 #
1"
#1752000
0"
#1756000
b11011100 #
1"
#1760000
0"
#1764000
b11011101 #
1"
#1768000
0"
#1772000
b11011110 #
1"
#1776000
0"
#1780000
b11011111 #
1"
#1784000
0"
#1788000
b11100000 #
1"
#1792000
0"
#1796000
b11100001 #
1"
#1800000
0"
#1804000
b11100010 #
1"
#1808000
0"
#1812000
b11100011 #
1"
#1816000
0"
#1820000
b11100100 #
1"
#1824000
0"
#1828000
b11100101 #
1"
#1832000
0"
#1836000
b11100110 #
1"
#1840000
0"
#1844000
b11100111 #
1"
#1848000
0"
#1852000
b11101000 #
1"
#1856000
0"
#1860000
b11101001 #
1"
#1864000
0"
#1868000
b11101010 #
1"
#1872000
0"
#1876000
b11101011 #
1"
#1880000
0"
#1884000
b11101100 #
1"
#1888000
0"
#1892000
b11101101 #
1"
#1896000
0"
#1900000
b11101110 #
1"
#1904000
0"
#1908000
b11101111 #
1"
#1912000
0"
#1916000
b11110000 #
1"
#1920000
0"
#1924000
b11110001 #
1"
#1928000
0"
#1932000
b11110010 #
1"
#1936000
0"
#1940000
b11110011 #
1"
#1944000
0"
#1948000
b11110100 #
1"
#1952000
0"
#1956000
b11110101 #
1"
#1960000
0"
#1964000
b11110110 #
1"
#1968000
0"
#1972000
b11110111 #
1"
#1976000
0"
#1980000
b11111000 #
1"
#1984000
0"
#1988000
b11111001 #
1"
#1992000
0"
#1996000
b11111010 #
1"
